hs_scraper_toolkit/__init__.py
hs_scraper_toolkit/Athletics/AthleticNetTrackField.py
hs_scraper_toolkit/Athletics/MaxPrepRoster.py
hs_scraper_toolkit/Athletics/__init__.py
hs_scraper_toolkit/Northside/AthleticsSchedule.py
hs_scraper_toolkit/Northside/GeneralEvent.py
hs_scraper_toolkit/Northside/__init__.py
hs_scraper_toolkit-1.1.0.dist-info/licenses/LICENSE
hs_scraper_toolkit-1.1.0.dist-info/METADATA
hs_scraper_toolkit-1.1.0.dist-info/WHEEL
hs_scraper_toolkit-1.1.0.dist-info/top_level.txt
hs_scraper_toolkit-1.1.0.dist-info/RECORD
