Metadata-Version: 2.4
Name: hs-scraper-toolkit
Version: 1.1.0
Summary: A comprehensive toolkit for scraping high school data with school-specific modules
Author-email: Tanmay Garg <stampede.ncp@gmail.com>
License-Expression: MIT
Project-URL: Homepage, https://github.com/NCP-Stampede/hs-scraper-toolkit
Project-URL: Documentation, https://github.com/NCP-Stampede/hs-scraper-toolkit#readme
Project-URL: Repository, https://github.com/NCP-Stampede/hs-scraper-toolkit
Project-URL: Bug Tracker, https://github.com/NCP-Stampede/hs-scraper-toolkit/issues
Keywords: scraping,sports,high school,athletics,maxpreps,athletic.net,track,field,cross-country,school-specific,schedule,events,northside
Classifier: Development Status :: 4 - Beta
Classifier: Intended Audience :: Developers
Classifier: Programming Language :: Python :: 3
Classifier: Programming Language :: Python :: 3.7
Classifier: Programming Language :: Python :: 3.8
Classifier: Programming Language :: Python :: 3.9
Classifier: Programming Language :: Python :: 3.10
Classifier: Programming Language :: Python :: 3.11
Requires-Python: >=3.7
License-File: LICENSE
Requires-Dist: beautifulsoup4>=4.9.0
Requires-Dist: requests>=2.25.0
Requires-Dist: pandas>=1.3.0
Requires-Dist: selenium>=4.0.0
Provides-Extra: dev
Requires-Dist: pytest>=6.0; extra == "dev"
Requires-Dist: black>=21.0; extra == "dev"
Requires-Dist: flake8>=3.8; extra == "dev"
Dynamic: license-file
